microsoft/__init__.py
microsoft/bing/__init__.py
microsoft/bing/commerce/__init__.py
microsoft/bing/commerce/search/__init__.py
microsoft/bing/commerce/search/bing_commerce_search.py
microsoft/bing/commerce/search/version.py
microsoft/bing/commerce/search/models/__init__.py
microsoft/bing/commerce/search/models/bing_commerce_search_enums.py
microsoft/bing/commerce/search/models/bool_condition.py
microsoft/bing/commerce/search/models/bool_condition_py3.py
microsoft/bing/commerce/search/models/boost_expression.py
microsoft/bing/commerce/search/models/boost_expression_py3.py
microsoft/bing/commerce/search/models/category_condition.py
microsoft/bing/commerce/search/models/category_condition_py3.py
microsoft/bing/commerce/search/models/commerce_search_post_request.py
microsoft/bing/commerce/search/models/commerce_search_post_request_py3.py
microsoft/bing/commerce/search/models/commerce_search_response.py
microsoft/bing/commerce/search/models/commerce_search_response_py3.py
microsoft/bing/commerce/search/models/condition_base.py
microsoft/bing/commerce/search/models/condition_base_py3.py
microsoft/bing/commerce/search/models/condition_block.py
microsoft/bing/commerce/search/models/condition_block_py3.py
microsoft/bing/commerce/search/models/equivalence_condition_base.py
microsoft/bing/commerce/search/models/equivalence_condition_base_py3.py
microsoft/bing/commerce/search/models/field_condition_base.py
microsoft/bing/commerce/search/models/field_condition_base_py3.py
microsoft/bing/commerce/search/models/geo_boundary_base.py
microsoft/bing/commerce/search/models/geo_boundary_base_py3.py
microsoft/bing/commerce/search/models/geo_bounding_box.py
microsoft/bing/commerce/search/models/geo_bounding_box_py3.py
microsoft/bing/commerce/search/models/geo_condition.py
microsoft/bing/commerce/search/models/geo_condition_py3.py
microsoft/bing/commerce/search/models/geo_distance.py
microsoft/bing/commerce/search/models/geo_distance_py3.py
bing_commerce_search-1.0.0.dist-info/METADATA
bing_commerce_search-1.0.0.dist-info/WHEEL
bing_commerce_search-1.0.0.dist-info/top_level.txt
bing_commerce_search-1.0.0.dist-info/RECORD
